spec_server/__init__.py
spec_server/__main__.py
spec_server/config.py
spec_server/content_classifier.py
spec_server/design_element_formatter.py
spec_server/design_format_detector.py
spec_server/design_template_manager.py
spec_server/document_generator.py
spec_server/errors.py
spec_server/llm_guidance.py
spec_server/llm_task_validator.py
spec_server/main.py
spec_server/mcp_tools.py
spec_server/models.py
spec_server/requirements_linker.py
spec_server/server.py
spec_server/spec_manager.py
spec_server/task_executor.py
spec_server/task_formatter.py
spec_server/task_formatting_cache.py
spec_server/task_formatting_config.py
spec_server/task_formatting_errors.py
spec_server/task_parser.py
spec_server/task_renderer.py
spec_server/validation.py
spec_server/workflow_engine.py
spec_server-0.6.3.dist-info/METADATA
spec_server-0.6.3.dist-info/WHEEL
spec_server-0.6.3.dist-info/entry_points.txt
spec_server-0.6.3.dist-info/licenses/LICENSE
spec_server-0.6.3.dist-info/RECORD
