Metadata-Version: 2.4
Name: spec-server
Version: 0.6.3
Summary: MCP server for structured feature development through Requirements → Design → Tasks workflow
Project-URL: Homepage, https://github.com/teknologika/spec-server
Project-URL: Repository, https://github.com/teknologika/spec-server
Project-URL: Issues, https://github.com/teknologika/spec-server/issues
Author-email: Teknologika <hello@teknologika.com>
License: MIT
License-File: LICENSE
Keywords: design,feature-development,mcp,requirements,specification,tasks,workflow
Classifier: Development Status :: 3 - Alpha
Classifier: Environment :: Console
Classifier: Intended Audience :: Developers
Classifier: License :: OSI Approved :: MIT License
Classifier: Operating System :: OS Independent
Classifier: Programming Language :: Python :: 3
Classifier: Programming Language :: Python :: 3.12
Classifier: Topic :: Software Development
Classifier: Topic :: Software Development :: Documentation
Classifier: Topic :: Software Development :: Libraries :: Python Modules
Classifier: Topic :: Text Processing :: Markup :: Markdown
Requires-Python: >=3.12
Requires-Dist: fastmcp>=0.2.0
Requires-Dist: pathlib-mate>=1.0.0
Requires-Dist: pydantic>=2.0.0
Provides-Extra: dev
Requires-Dist: black>=23.0.0; extra == 'dev'
Requires-Dist: flake8>=6.0.0; extra == 'dev'
Requires-Dist: isort>=5.12.0; extra == 'dev'
Requires-Dist: mypy>=1.0.0; extra == 'dev'
Requires-Dist: pytest-asyncio>=0.21.0; extra == 'dev'
Requires-Dist: pytest-cov>=4.0.0; extra == 'dev'
Requires-Dist: pytest>=7.0.0; extra == 'dev'
